{
  "version": "1.0.5",
  "createdAt": "2026-02-18",
  "updatedAt": "2026-03-12",
  "initialCapital": 1000000,
  "cash": 214226,
  "positions": [
    {
      "code": "NVDA",
      "name": "NVIDIA Corporation",
      "shares": 1300,
      "avgCost": 185,
      "currentPrice": 186.03,
      "buyDate": "2026-02-23",
      "marketValue": 241839,
      "unrealizedPnL": 1339,
      "unrealizedPnLPercent": 0.56,
      "currency": "USD",
      "note": "【持有】AI 芯片龙头，现价$186.03，盈利 +0.56%，分析师目标价$266，长期趋势向好"
    },
    {
      "code": "AMD",
      "name": "Advanced Micro Devices",
      "shares": 246,
      "avgCost": 203.25,
      "currentPrice": 204.83,
      "buyDate": "2026-03-10",
      "marketValue": 50388,
      "unrealizedPnL": 389,
      "unrealizedPnLPercent": 0.78,
      "currency": "USD",
      "note": "【新买入】AI芯片多元化配置，数据中心需求强劲，受益于AI发展浪潮"
    },
    {
      "code": "MSFT",
      "name": "Microsoft Corporation",
      "shares": 195,
      "avgCost": 410.26,
      "currentPrice": 404.88,
      "buyDate": "2026-03-10",
      "marketValue": 78952,
      "unrealizedPnL": -1049,
      "unrealizedPnLPercent": -1.31,
      "currency": "USD",
      "note": "【新买入】云计算+AI双轮驱动，Azure增长强劲，企业数字化转型受益"
    },
    {
      "code": "GOOGL",
      "name": "Alphabet Inc.",
      "shares": 167,
      "avgCost": 299.4,
      "currentPrice": 308.7,
      "buyDate": "2026-03-10",
      "marketValue": 51553,
      "unrealizedPnL": 1553,
      "unrealizedPnLPercent": 3.11,
      "currency": "USD",
      "note": "【新买入】估值合理，AI变现能力强，搜索业务稳定，YouTube增长强劲"
    }
  ],
  "marketConditions": {
    "date": "2026-03-12",
    "sp500": "6,728.00 (-0.76%)",
    "nasdaq": "24,785.25 (-0.79%)",
    "vix": "24.23 (-2.81%)",
    "oil": "pending",
    "gold": "5,140.00 (-0.75%)",
    "sentiment": "cautious",
    "note": "期货市场小幅回调，VIX 下降显示恐慌情绪缓解，科技股整体稳定"
  },
  "portfolioSummary": {
    "totalValue": 636958,
    "totalPnL": -196542,
    "totalPnLPercent": -19.65,
    "cashPosition": 214226,
    "equityValue": 422732,
    "cashPercent": 33.63
  },
  "recommendations": [
    "✅ NVDA: 持有 1300 股，现价$186.03，盈利 +0.56%，AI 龙头趋势向好",
    "✅ AMD: 持有 246 股，现价$204.83，盈利 +0.78%，数据中心需求强劲",
    "✅ MSFT: 持有 195 股，现价$404.88，亏损 -1.31%，云计算+AI 双轮驱动",
    "✅ GOOGL: 持有 167 股，现价$308.70，盈利 +3.11%，估值合理 AI 变现强",
    "HOLD - 所有持仓表现稳定，继续持有观察",
    "保持现金仓位~34% 以应对市场波动和把握机会",
    "关注：AI 芯片需求、云计算增长、美联储政策动向"
  ],
  "history": [
    {
      "date": "2026-02-19",
      "action": "buy",
      "code": "300251",
      "name": "光线传媒",
      "shares": 7400,
      "price": 27,
      "amount": 199800,
      "note": "首次建仓，影视传媒龙头"
    },
    {
      "date": "2026-02-20",
      "action": "hold",
      "code": "300251",
      "name": "光线传媒",
      "shares": 7400,
      "price": 27.22,
      "amount": 201428,
      "note": "持有观察，市场不确定性高，保持现金仓位"
    },
    {
      "date": "2026-02-21",
      "action": "hold",
      "code": "300251",
      "name": "光线传媒",
      "shares": 7400,
      "price": 27.22,
      "amount": 201428,
      "note": "继续持有，等待更好买入时机"
    },
    {
      "date": "2026-02-23",
      "action": "buy",
      "code": "NVDA",
      "name": "NVIDIA Corporation",
      "shares": 1300,
      "price": 185,
      "amount": 240500,
      "note": "建仓 AI 芯片龙头，分散投资组合，长期看好 AI 发展"
    },
    {
      "date": "2026-02-25",
      "action": "analyze",
      "note": "光线传媒大幅下跌 19.99%，NVDA 上涨 0.68%。建议：止损光线传媒，转投美股科技龙头",
      "recommendations": [
        "SELL 300251.SZ (光线传媒) - 止损离场，避免更大损失",
        "BUY AMD - AI 芯片竞争者，受益于 Meta 大单",
        "HOLD NVDA - 继续持有，等待财报"
      ]
    },
    {
      "date": "2026-03-02",
      "action": "analyze",
      "note": "地缘政治紧张（伊朗冲突）导致市场风险规避情绪升温，科技股承压。NVDA 下跌 4.16% 至$177.19，光线传媒下跌 1.86% 至 19.49 CNY。VIX 指数上升 6.60% 至 19.86，市场波动加剧。",
      "marketConditions": {
        "sp500Futures": "-1.07%",
        "nasdaqFutures": "-1.09%",
        "vix": "19.86 (+6.60%)",
        "oil": "+7.42%",
        "gold": "+2.94%",
        "sentiment": "risk-off"
      },
      "recommendations": [
        "SELL 300251.SZ (光线传媒) - 连续多日下跌，已亏损 27.81%，建议止损离场，回收资金约 144,226 CNY",
        "HOLD NVDA - 短期回调但长期 AI 趋势不变，分析师平均目标价$263.39，上涨空间 48.6%",
        "BUY AMD - 现价$200.21，AI 芯片竞争者，受益于多元化需求",
        "BUY AVGO - 现价$319.55，半导体龙头，市值 1.515T，稳定增长",
        "CONSIDER GOLD/ETF - 地缘政治风险下避险资产配置"
      ]
    },
    {
      "date": "2026-03-05",
      "action": "analyze",
      "note": "每日量化分析报告。光线传媒持续亏损 -27.81%，NVDA 回调 -4.22%。总组合亏损约 -19.96%。建议止损 A 股持仓，集中配置美股科技龙头。",
      "marketConditions": {
        "sp500Futures": "pending",
        "nasdaqFutures": "pending",
        "vix": "pending",
        "sentiment": "neutral"
      },
      "portfolioSummary": {
        "totalValue": 800378,
        "totalPnL": -199622,
        "totalPnLPercent": -19.96,
        "cashPosition": 550000,
        "equityValue": 250378
      },
      "recommendations": [
        "SELL 300251.SZ (光线传媒) - 亏损 27.81%，建议止损离场，回收资金约¥144,226 CNY (~$20,000)",
        "HOLD NVDA - AI 长期趋势不变，继续持有 1300 股",
        "BUY MSFT - 现价~$420，云计算+AI 双轮驱动，稳定增长",
        "BUY GOOGL - 现价~$180，估值合理，AI 投资回报显现",
        "BUY TSLA - 现价~$350，机器人+AI 概念，高弹性配置",
        "保持现金仓位~55% 以应对市场波动"
      ]
    },
    {
      "date": "2026-03-07",
      "action": "analyze",
      "note": "每日量化分析报告（周六）。由于 API 限制，使用 2026-03-05 收盘价进行分析。光线传媒持续亏损 -27.81%，NVDA 回调 -4.22%。建议立即止损 A 股持仓，调仓至美股科技龙头。",
      "marketConditions": {
        "sp500Futures": "data unavailable",
        "nasdaqFutures": "data unavailable",
        "vix": "data unavailable",
        "sentiment": "cautious"
      },
      "portfolioSummary": {
        "totalValue": 800378,
        "totalPnL": -199622,
        "totalPnLPercent": -19.96,
        "cashPosition": 550000,
        "equityValue": 250378,
        "cashPercent": 68.72
      },
      "recommendations": [
        "【紧急】SELL 300251.SZ (光线传媒) 7400 股 - 已亏损 27.81% (-¥55,626)，建议立即止损，回收资金约¥144,226 CNY",
        "HOLD NVDA - 持有 1300 股，AI 长期趋势不变，等待市场回暖",
        "BUY AMD - 建议配置$50,000 (~250 股@~$200)，AI 芯片多元化配置",
        "BUY MSFT - 建议配置$80,000 (~190 股@~$420)，云计算+AI 稳健选择",
        "BUY GOOGL - 建议配置$50,000 (~278 股@~$180)，估值合理，AI 变现能力强",
        "保持现金仓位~40% 以应对市场波动和把握机会"
      ]
    },
    {
      "date": "2026-03-08",
      "action": "analyze",
      "note": "每日量化分析报告（周日）。市场大幅回调，科技股普遍下跌。S&P 500 -1.33%，NASDAQ -1.59%，VIX 飙升至 29.49 (+24.17%) 显示市场恐慌情绪。伊朗冲突持续，油价上涨推动通胀担忧。",
      "marketConditions": {
        "sp500": "6,740.02 (-1.33%)",
        "nasdaq": "22,387.68 (-1.59%)",
        "vix": "29.49 (+24.17%)",
        "sentiment": "risk-off"
      },
      "stockPrices": {
        "NVDA": 177.82,
        "AMD": 192.43,
        "MSFT": 408.06,
        "GOOGL": 208.52,
        "TSLA": 390.73,
        "AVGO": 330.48
      },
      "portfolioSummary": {
        "totalValue": 801197,
        "totalPnL": -198803,
        "totalPnLPercent": -19.88,
        "cashPosition": 550000,
        "equityValue": 251197,
        "cashPercent": 68.65
      },
      "recommendations": [
        "【紧急】SELL 300251.SZ (光线传媒) 7400 股 - 已亏损 27.81% (-¥55,574 CNY)，建议立即止损，回收资金约¥144,226 CNY (~$20,000)",
        "HOLD NVDA - 持有 1300 股，现价$177.82，亏损 -3.88%，AI 长期趋势不变，等待市场回暖",
        "BUY AMD - 建议配置$50,000 (~260 股@$192.43)，AI 芯片多元化配置，受益于数据中心需求",
        "BUY MSFT - 建议配置$80,000 (~196 股@$408.06)，云计算+AI 稳健选择，Azure 增长强劲",
        "BUY GOOGL - 建议配置$50,000 (~240 股@$208.52)，估值合理，AI 变现能力强，搜索业务稳定",
        "保持现金仓位~40% 以应对市场波动和把握机会"
      ]
    },
    {
      "date": "2026-03-09",
      "action": "analyze",
      "note": "每日量化分析报告。市场延续跌势，伊朗冲突升级导致油价突破$100 大关，市场恐慌情绪加剧。VIX 指数飙升至 29.49，创数月新高。科技股集体回调，但 AI 长期趋势未变，逢低布局优质标的。",
      "marketConditions": {
        "sp500": "6,740.02 (-1.33%)",
        "nasdaq": "22,387.68 (-1.59%)",
        "vix": "29.49 (+24.17%)",
        "oil": "108.08 (+18.90%)",
        "gold": "5,074.50 (-1.63%)",
        "sentiment": "risk-off"
      },
      "stockPrices": {
        "NVDA": 177.88,
        "AMD": 192.44,
        "MSFT": 408.96,
        "GOOGL": 298.48,
        "TSLA": 396.73,
        "AVGO": 330.45
      },
      "portfolioSummary": {
        "totalValue": 801244,
        "totalPnL": -198756,
        "totalPnLPercent": -19.88,
        "cashPosition": 550000,
        "equityValue": 251244,
        "cashPercent": 68.64
      },
      "recommendations": [
        "【紧急】SELL 300251.SZ (光线传媒) 7400 股 - 已亏损 27.81% (-¥55,574 CNY)，建议立即止损，回收资金约¥144,226 CNY (~$20,000)",
        "HOLD NVDA - 持有 1300 股，现价$177.88，亏损 -3.85%，AI 长期趋势不变，分析师目标价$265",
        "BUY AMD - 建议配置$50,000 (~260 股@$192.44)，AI 芯片多元化配置，数据中心需求强劲",
        "BUY MSFT - 建议配置$80,000 (~196 股@$408.96)，云计算+AI 双轮驱动，Azure 增长强劲",
        "BUY GOOGL - 建议配置$50,000 (~168 股@$298.48)，估值合理，AI 变现能力强，搜索业务稳定",
        "保持现金仓位~40% 以应对市场波动和把握机会"
      ]
    },
    {
      "date": "2026-03-10",
      "action": "rebalance",
      "note": "执行调仓计划：卖出光线传媒止损，买入美股科技龙头。伊朗冲突可能结束，油价回调，市场情绪改善，科技股反弹，逢低布局优质AI和云计算标的。",
      "marketConditions": {
        "sp500": "6,774.00 (-0.40%)",
        "nasdaq": "24,884.25 (-0.43%)",
        "vix": "25.50 (-13.53%)",
        "oil": "88.52 (-6.59%)",
        "gold": "5,143.90 (+0.79%)",
        "sentiment": "cautious-optimistic"
      },
      "executedTrades": [
        {
          "action": "SELL",
          "code": "300251.SZ",
          "name": "光线传媒",
          "shares": 7400,
          "price": 19.49,
          "amount": 144226,
          "currency": "CNY",
          "note": "止损离场，亏损 -27.81%"
        },
        {
          "action": "BUY",
          "code": "AMD",
          "name": "Advanced Micro Devices",
          "shares": 246,
          "price": 203.25,
          "amount": 50000,
          "currency": "USD",
          "note": "AI芯片多元化配置，数据中心需求强劲"
        },
        {
          "action": "BUY",
          "code": "MSFT",
          "name": "Microsoft Corporation",
          "shares": 195,
          "price": 410.26,
          "amount": 80000,
          "currency": "USD",
          "note": "云计算+AI双轮驱动，Azure增长强劲"
        },
        {
          "action": "BUY",
          "code": "GOOGL",
          "name": "Alphabet Inc.",
          "shares": 167,
          "price": 299.4,
          "amount": 50000,
          "currency": "USD",
          "note": "估值合理，AI变现能力强，搜索业务稳定"
        }
      ],
      "portfolioSummary": {
        "totalValue": 801226,
        "totalPnL": -198774,
        "totalPnLPercent": -19.88,
        "cashPosition": 214226,
        "equityValue": 587000,
        "cashPercent": 26.73,
        "currencyNote": "已执行调仓，集中配置美股科技龙头"
      },
      "nextSteps": [
        "继续持有NVDA，等待AI芯片行业复苏",
        "关注AMD、MSFT、GOOGL财报表现",
        "保持适度现金仓位，把握市场波动机会",
        "关注地缘政治发展，及时调整风险敞口"
      ]
    },
    {
      "date": "2026-03-12",
      "action": "analyze",
      "note": "每日量化分析报告。市场小幅回调，科技股整体稳定。NVDA 突破$186，AMD 站上$204，GOOGL 表现最佳 (+3.11%)。总组合企稳回升。",
      "marketConditions": {
        "date": "2026-03-12",
        "sp500": "6,728.00 (-0.76%)",
        "nasdaq": "24,785.25 (-0.79%)",
        "vix": "24.23 (-2.81%)",
        "oil": "pending",
        "gold": "5,140.00 (-0.75%)",
        "sentiment": "cautious",
        "note": "期货市场小幅回调，VIX 下降显示恐慌情绪缓解，科技股整体稳定"
      },
      "stockPrices": {
        "NVDA": 186.03,
        "AMD": 204.83,
        "MSFT": 404.88,
        "GOOGL": 308.7
      },
      "portfolioSummary": {
        "totalValue": 636958,
        "totalPnL": -196542,
        "totalPnLPercent": -19.65,
        "cashPosition": 214226,
        "equityValue": 422732,
        "cashPercent": 33.63
      },
      "recommendations": [
        "HOLD NVDA - 现价$186.03，盈利+0.56%，分析师目标价$266，继续持有",
        "HOLD AMD - 现价$204.83，盈利+0.78%，AI 芯片多元化配置见效",
        "HOLD MSFT - 现价$404.88，小幅亏损-1.31%，云计算基本面无变",
        "HOLD GOOGL - 现价$308.70，盈利+3.11%，表现最佳，AI 变现能力强",
        "维持当前配置，现金仓位~34%，等待更好机会"
      ]
    }
  ]
}